samtts/__init__.py
samtts/__main__.py
samtts/processor.py
samtts/reciter.py
samtts/renderer.py
samtts/samtts.py
samtts-0.2.0.dist-info/METADATA
samtts-0.2.0.dist-info/WHEEL
samtts-0.2.0.dist-info/entry_points.txt
samtts-0.2.0.dist-info/top_level.txt
samtts-0.2.0.dist-info/RECORD
