Metadata-Version: 2.4
Name: samtts
Version: 0.2.0
Summary: A Python port of Software Automatic Mouth Test-To-Speech program.
Author-email: Quan Lin <jacklinquan@gmail.com>
Project-URL: Homepage, https://github.com/jacklinquan/samtts
Keywords: sam,tts
Classifier: Programming Language :: Python :: 3
Requires-Python: >=3.8
Requires-Dist: simpleaudio
Requires-Dist: typer
Provides-Extra: dev
Requires-Dist: simpleaudio; extra == "dev"
Requires-Dist: typer; extra == "dev"
Requires-Dist: pytest; extra == "dev"
Requires-Dist: mkdocs; extra == "dev"
Requires-Dist: mkdocstrings-python; extra == "dev"
Requires-Dist: black; extra == "dev"
